[
  {
    "Title": "Tere Ishk Mein",
    "Poster": "https://in.bmscdn.com/events/moviecard/tere-ishk-mein-et00465226-1759315704.jpg",
    "Genres": [
      "Drama",
      "Romantic"
    ],
    "Rating": "UA16",
    "Duration": "2 hrs 49 mins",
    "EventDate": "2025-11-28",
    "isNewEvent": "Y",
    "CityCount": 180,
    "DefaultEventCode": "ET00362760",
    "Variants": [
      {
        "VariantName": "Tere Ishk Mein",
        "EventCode": "ET00362760",
        "Language": "Hindi",
        "Format": "2D",
        "CityCount": 158
      },
      {
        "VariantName": "Tere Ishk Mein (Tamil)",
        "EventCode": "ET00465226",
        "Language": "Tamil",
        "Format": "2D",
        "CityCount": 35
      }
    ]
  },
  {
    "Title": "Zootopia 2",
    "Poster": "https://in.bmscdn.com/events/moviecard/zootopia-2-et00441877-1763635925.jpg",
    "Genres": [
      "Adventure",
      "Animation",
      "Comedy"
    ],
    "Rating": "UA 7",
    "Duration": "1 hr 48 mins",
    "EventDate": "2025-11-28",
    "isNewEvent": "Y",
    "CityCount": 79,
    "DefaultEventCode": "ET00441877",
    "Variants": [
      {
        "VariantName": "Zootopia 2",
        "EventCode": "ET00441877",
        "Language": "English",
        "Format": "2D",
        "CityCount": 7
      },
      {
        "VariantName": "Zootopia 2 (3D)(Hindi)",
        "EventCode": "ET00472393",
        "Language": "Hindi",
        "Format": "3D",
        "CityCount": 34
      },
      {
        "VariantName": "Zootopia 2 (3D)",
        "EventCode": "ET00472345",
        "Language": "English",
        "Format": "3D",
        "CityCount": 29
      },
      {
        "VariantName": "Zootopia 2 (Hindi)",
        "EventCode": "ET00469075",
        "Language": "Hindi",
        "Format": "2D",
        "CityCount": 19
      },
      {
        "VariantName": "Zootopia 2 (3D)(Tamil)",
        "EventCode": "ET00472398",
        "Language": "Tamil",
        "Format": "3D",
        "CityCount": 8
      },
      {
        "VariantName": "Zootopia 2 (3D)(Telugu)",
        "EventCode": "ET00472205",
        "Language": "Telugu",
        "Format": "3D",
        "CityCount": 6
      },
      {
        "VariantName": "Zootopia 2 (Telugu)",
        "EventCode": "ET00469077",
        "Language": "Telugu",
        "Format": "2D",
        "CityCount": 4
      },
      {
        "VariantName": "Zootopia 2 (IMAX 3D)",
        "EventCode": "ET00472717",
        "Language": "English",
        "Format": "IMAX 3D",
        "CityCount": 2
      },
      {
        "VariantName": "Zootopia 2 (4DX 3D)",
        "EventCode": "ET00472722",
        "Language": "English",
        "Format": "4DX 3D",
        "CityCount": 2
      },
      {
        "VariantName": "Zootopia 2 (Tamil)",
        "EventCode": "ET00469076",
        "Language": "Tamil",
        "Format": "2D",
        "CityCount": 2
      },
      {
        "VariantName": "Zootopia 2 (4DX 3D)(Hindi)",
        "EventCode": "ET00472776",
        "Language": "Hindi",
        "Format": "4DX 3D",
        "CityCount": 1
      }
    ]
  },
  {
    "Title": "Andhra King Taluka",
    "Poster": "https://in.bmscdn.com/events/moviecard/andhra-king-taluka-et00446228-1747376210.jpg",
    "Genres": [
      "Action",
      "Comedy",
      "Drama",
      "Romantic"
    ],
    "Rating": "UA13",
    "Duration": "2 hrs 46 mins",
    "EventDate": "2025-11-27",
    "isNewEvent": "Y",
    "CityCount": 62,
    "DefaultEventCode": "ET00446228",
    "Variants": [
      {
        "VariantName": "Andhra King Taluka",
        "EventCode": "ET00446228",
        "Language": "Telugu",
        "Format": "2D",
        "CityCount": 59
      },
      {
        "VariantName": "Andhra King Taluka (Kannada)",
        "EventCode": "ET00472627",
        "Language": "Kannada",
        "Format": "2D",
        "CityCount": 5
      }
    ]
  },
  {
    "Title": "Revolver Rita",
    "Poster": "https://in.bmscdn.com/events/moviecard/revolver-rita-et00471947-1763710659.jpg",
    "Genres": [
      "Action",
      "Comedy",
      "Crime"
    ],
    "Rating": "UA16",
    "Duration": "2 hrs 22 mins",
    "EventDate": "2025-11-28",
    "isNewEvent": "Y",
    "CityCount": 42,
    "DefaultEventCode": "ET00471947",
    "Variants": [
      {
        "VariantName": "Revolver Rita",
        "EventCode": "ET00471947",
        "Language": "Tamil",
        "Format": "2D",
        "CityCount": 32
      },
      {
        "VariantName": "Revolver Rita (Telugu)",
        "EventCode": "ET00471948",
        "Language": "Telugu",
        "Format": "2D",
        "CityCount": 10
      }
    ]
  },
  {
    "Title": "Mastiii 4",
    "Poster": "https://in.bmscdn.com/events/moviecard/mastiii-4-et00464040-1764352224.jpg",
    "Genres": [
      "Adult",
      "Comedy"
    ],
    "Rating": "A",
    "Duration": "2 hrs 22 mins",
    "EventDate": "2025-11-21",
    "isNewEvent": "N",
    "CityCount": 37,
    "DefaultEventCode": "ET00464040",
    "Variants": [
      {
        "VariantName": "Mastiii 4",
        "EventCode": "ET00464040",
        "Language": "Hindi",
        "Format": "2D",
        "CityCount": 37
      }
    ]
  },
  {
    "Title": "Raju Weds Rambai",
    "Poster": "https://in.bmscdn.com/events/moviecard/raju-weds-rambai-et00471442-1763704957.jpg",
    "Genres": [
      "Drama",
      "Romantic"
    ],
    "Rating": "UA16",
    "Duration": "2 hrs 15 mins",
    "EventDate": "2025-11-21",
    "isNewEvent": "N",
    "CityCount": 34,
    "DefaultEventCode": "ET00471442",
    "Variants": [
      {
        "VariantName": "Raju Weds Rambai",
        "EventCode": "ET00471442",
        "Language": "Telugu",
        "Format": "2D",
        "CityCount": 34
      }
    ]
  },
  {
    "Title": "Eko",
    "Poster": "https://in.bmscdn.com/events/moviecard/eko-et00470809-1763016041.jpg",
    "Genres": [
      "Drama",
      "Mystery"
    ],
    "Rating": "UA16",
    "Duration": "2 hrs 7 mins",
    "EventDate": "2025-11-21",
    "isNewEvent": "N",
    "CityCount": 34,
    "DefaultEventCode": "ET00470809",
    "Variants": [
      {
        "VariantName": "Eko",
        "EventCode": "ET00470809",
        "Language": "Malayalam",
        "Format": "2D",
        "CityCount": 34
      }
    ]
  },
  {
    "Title": "De De Pyaar De 2",
    "Poster": "https://in.bmscdn.com/events/moviecard/de-de-pyaar-de-2-et00391156-1764502961.jpg",
    "Genres": [
      "Comedy",
      "Family",
      "Romantic"
    ],
    "Rating": "UA13",
    "Duration": "2 hrs 27 mins",
    "EventDate": "2025-11-14",
    "isNewEvent": "N",
    "CityCount": 33,
    "DefaultEventCode": "ET00391156",
    "Variants": [
      {
        "VariantName": "De De Pyaar De 2",
        "EventCode": "ET00391156",
        "Language": "Hindi",
        "Format": "2D",
        "CityCount": 33
      }
    ]
  },
  {
    "Title": "Dhurandhar",
    "Poster": "https://in.bmscdn.com/events/moviecard/dhurandhar-et00452447-1763469106.jpg",
    "Genres": [
      "Action",
      "Thriller"
    ],
    "Rating": "A",
    "Duration": "3 hrs 30 mins",
    "EventDate": "2025-12-05",
    "isNewEvent": "Y",
    "CityCount": 31,
    "DefaultEventCode": "ET00452447",
    "Variants": [
      {
        "VariantName": "Dhurandhar",
        "EventCode": "ET00452447",
        "Language": "Hindi",
        "Format": "2D",
        "CityCount": 31
      }
    ]
  },
  {
    "Title": "120 Bahadur",
    "Poster": "https://in.bmscdn.com/events/moviecard/120-bahadur-et00410659-1763551608.jpg",
    "Genres": [
      "Action",
      "Historical",
      "War"
    ],
    "Rating": "UA13",
    "Duration": "2 hrs 17 mins",
    "EventDate": "2025-11-21",
    "isNewEvent": "N",
    "CityCount": 25,
    "DefaultEventCode": "ET00410659",
    "Variants": [
      {
        "VariantName": "120 Bahadur",
        "EventCode": "ET00410659",
        "Language": "Hindi",
        "Format": "2D",
        "CityCount": 25
      }
    ]
  },
  {
    "Title": "Businessman ",
    "Poster": "https://in.bmscdn.com/events/moviecard/businessman-et00008299-1763800903.jpg",
    "Genres": [
      "Action",
      "Drama"
    ],
    "Rating": "A",
    "Duration": "2 hrs 13 mins",
    "EventDate": "2012-01-11",
    "isNewEvent": "N",
    "CityCount": 23,
    "DefaultEventCode": "ET00008299",
    "Variants": [
      {
        "VariantName": "Businessman",
        "EventCode": "ET00008299",
        "Language": "Telugu",
        "Format": "2D",
        "CityCount": 23
      }
    ]
  },
  {
    "Title": "Vilayath Budha",
    "Poster": "https://in.bmscdn.com/events/moviecard/vilaayath-budha-et00471246-1763446137.jpg",
    "Genres": [
      "Action",
      "Thriller"
    ],
    "Rating": "UA16",
    "Duration": "2 hrs 45 mins",
    "EventDate": "2025-11-21",
    "isNewEvent": "N",
    "CityCount": 20,
    "DefaultEventCode": "ET00471246",
    "Variants": [
      {
        "VariantName": "Vilayath Budha",
        "EventCode": "ET00471246",
        "Language": "Malayalam",
        "Format": "2D",
        "CityCount": 20
      }
    ]
  },
  {
    "Title": "Laalo - Krishna Sada Sahaayate",
    "Poster": "https://in.bmscdn.com/events/moviecard/laalo--krishna-sada-sahaayate-et00459408-1756649611.jpg",
    "Genres": [
      "Drama"
    ],
    "Rating": "UA13",
    "Duration": "2 hrs 15 mins",
    "EventDate": "2025-10-10",
    "isNewEvent": "N",
    "CityCount": 20,
    "DefaultEventCode": "ET00459408",
    "Variants": [
      {
        "VariantName": "Laalo - Krishna Sada Sahaayate",
        "EventCode": "ET00459408",
        "Language": "Gujarati",
        "Format": "2D",
        "CityCount": 20
      }
    ]
  },
  {
    "Title": "Gustaakh Ishq",
    "Poster": "https://in.bmscdn.com/events/moviecard/gustaakh-ishq-et00459660-1764072310.jpg",
    "Genres": [
      "Drama",
      "Romantic"
    ],
    "Rating": "UA13",
    "Duration": "2 hrs 8 mins",
    "EventDate": "2025-11-28",
    "isNewEvent": "Y",
    "CityCount": 15,
    "DefaultEventCode": "ET00459660",
    "Variants": [
      {
        "VariantName": "Gustaakh Ishq",
        "EventCode": "ET00459660",
        "Language": "Hindi",
        "Format": "2D",
        "CityCount": 15
      }
    ]
  },
  {
    "Title": "Mask (2025)",
    "Poster": "https://in.bmscdn.com/events/moviecard/mask-2025-et00470630-1762938809.jpg",
    "Genres": [
      "Comedy",
      "Thriller"
    ],
    "Rating": "UA16",
    "Duration": "2 hrs 7 mins",
    "EventDate": "2025-11-21",
    "isNewEvent": "N",
    "CityCount": 14,
    "DefaultEventCode": "ET00470630",
    "Variants": [
      {
        "VariantName": "Mask (2025)",
        "EventCode": "ET00470630",
        "Language": "Tamil",
        "Format": "2D",
        "CityCount": 14
      }
    ]
  },
  {
    "Title": "Yamla",
    "Poster": "https://in.bmscdn.com/events/moviecard/yamla-et00470801-1763015208.jpg",
    "Genres": [
      "Drama",
      "Romantic"
    ],
    "Rating": "U",
    "Duration": "2 hrs 14 mins",
    "EventDate": "2025-11-28",
    "isNewEvent": "Y",
    "CityCount": 12,
    "DefaultEventCode": "ET00470801",
    "Variants": [
      {
        "VariantName": "Yamla",
        "EventCode": "ET00470801",
        "Language": "Punjabi",
        "Format": "2D",
        "CityCount": 12
      }
    ]
  },
  {
    "Title": "Atmaharaam Live",
    "Poster": "https://in.bmscdn.com/events/moviecard/atmaharaam-live-et00472635-1764136733.jpg",
    "Genres": [
      "Comedy",
      "Horror"
    ],
    "Rating": "UA16",
    "Duration": "2 hrs 7 mins",
    "EventDate": "2025-11-28",
    "isNewEvent": "Y",
    "CityCount": 9,
    "DefaultEventCode": "ET00472635",
    "Variants": [
      {
        "VariantName": "Atmaharaam Live",
        "EventCode": "ET00472635",
        "Language": "Hindi",
        "Format": "2D",
        "CityCount": 9
      }
    ]
  },
  {
    "Title": "IPL: Indian Penal Law",
    "Poster": "https://in.bmscdn.com/events/moviecard/ipl-indian-penal-law-et00471994-1763722128.jpg",
    "Genres": [
      "Crime",
      "Political",
      "Thriller"
    ],
    "Rating": "UA16",
    "Duration": "2 hrs 8 mins",
    "EventDate": "2025-11-28",
    "isNewEvent": "Y",
    "CityCount": 9,
    "DefaultEventCode": "ET00471994",
    "Variants": [
      {
        "VariantName": "IPL: Indian Penal Law",
        "EventCode": "ET00471994",
        "Language": "Tamil",
        "Format": "2D",
        "CityCount": 9
      }
    ]
  },
  {
    "Title": "BP 180",
    "Poster": "https://in.bmscdn.com/events/moviecard/bp-180-et00470264-1762763302.jpg",
    "Genres": [
      "Crime",
      "Thriller"
    ],
    "Rating": "UA16",
    "Duration": "2 hrs 13 mins",
    "EventDate": "2025-11-28",
    "isNewEvent": "Y",
    "CityCount": 8,
    "DefaultEventCode": "ET00470264",
    "Variants": [
      {
        "VariantName": "BP 180",
        "EventCode": "ET00470264",
        "Language": "Tamil",
        "Format": "2D",
        "CityCount": 8
      }
    ]
  },
  {
    "Title": "Rangeela",
    "Poster": "https://in.bmscdn.com/events/moviecard/rangeela-et00470836-1763030942.jpg",
    "Genres": [
      "Comedy",
      "Drama",
      "Musical",
      "Romantic"
    ],
    "Rating": "U",
    "Duration": "2 hrs 30 mins",
    "EventDate": "1995-09-08",
    "isNewEvent": "N",
    "CityCount": 8,
    "DefaultEventCode": "ET00470836",
    "Variants": [
      {
        "VariantName": "Rangeela",
        "EventCode": "ET00470836",
        "Language": "Hindi",
        "Format": "2D",
        "CityCount": 8
      }
    ]
  },
  {
    "Title": "Spider-Man: Far From Home",
    "Poster": "https://in.bmscdn.com/events/moviecard/spider-man-far-from-home-et00106002-28-06-2019-04-58-31.jpg",
    "Genres": [
      "Action",
      "Adventure",
      "Comedy",
      "Fantasy"
    ],
    "Rating": "UA",
    "Duration": "2 hrs 9 mins",
    "EventDate": "2019-07-04",
    "isNewEvent": "N",
    "CityCount": 8,
    "DefaultEventCode": "ET00078437",
    "Variants": [
      {
        "VariantName": "Spider-Man: Far From Home",
        "EventCode": "ET00078437",
        "Language": "English",
        "Format": "2D",
        "CityCount": 5
      },
      {
        "VariantName": "Spider-Man: Far From Home (3D)",
        "EventCode": "ET00106002",
        "Language": "English",
        "Format": "3D",
        "CityCount": 2
      },
      {
        "VariantName": "Spider-Man: Far From Home (Tamil)",
        "EventCode": "ET00103093",
        "Language": "Tamil",
        "Format": "2D",
        "CityCount": 1
      }
    ]
  },
  {
    "Title": "Anjaan ",
    "Poster": "https://in.bmscdn.com/events/moviecard/anjaan-et00022730-1764070399.jpg",
    "Genres": [
      "Action",
      "Crime",
      "Thriller"
    ],
    "Rating": "U",
    "Duration": "2 hrs ",
    "EventDate": "2014-08-15",
    "isNewEvent": "N",
    "CityCount": 8,
    "DefaultEventCode": "ET00022730",
    "Variants": [
      {
        "VariantName": "Anjaan (Tamil)",
        "EventCode": "ET00022730",
        "Language": "Tamil",
        "Format": "2D",
        "CityCount": 8
      }
    ]
  },
  {
    "Title": "Attagasam",
    "Poster": "https://in.bmscdn.com/events/moviecard/attagasam-et00001340-1761724170.jpg",
    "Genres": [
      "Action",
      "Crime",
      "Drama"
    ],
    "Rating": "UA",
    "Duration": "2 hrs 37 mins",
    "EventDate": "2004-11-12",
    "isNewEvent": "N",
    "CityCount": 8,
    "DefaultEventCode": "ET00001340",
    "Variants": [
      {
        "VariantName": "Attagasam",
        "EventCode": "ET00001340",
        "Language": "Tamil",
        "Format": "2D",
        "CityCount": 8
      }
    ]
  },
  {
    "Title": "Ayyappanum Vapuranum",
    "Poster": "https://in.bmscdn.com/events/moviecard/ayyappanum-vapuranum-et00472654-1764308037.jpg",
    "Genres": [
      "Devotional",
      "Drama"
    ],
    "Rating": "U",
    "Duration": "1 hr 45 mins",
    "EventDate": "2025-11-28",
    "isNewEvent": "Y",
    "CityCount": 7,
    "DefaultEventCode": "ET00472654",
    "Variants": [
      {
        "VariantName": "Ayyappanum Vapuranum",
        "EventCode": "ET00472654",
        "Language": "Malayalam",
        "Format": "2D",
        "CityCount": 7
      }
    ]
  },
  {
    "Title": "Maruvatarama",
    "Poster": "https://in.bmscdn.com/events/moviecard/maruvatarama-et00472165-1763963441.jpg",
    "Genres": [
      "Drama",
      "Romantic"
    ],
    "Rating": "UA13",
    "Duration": "1 hr 52 mins",
    "EventDate": "2025-11-28",
    "isNewEvent": "Y",
    "CityCount": 7,
    "DefaultEventCode": "ET00472165",
    "Variants": [
      {
        "VariantName": "Maruvatarama",
        "EventCode": "ET00472165",
        "Language": "Telugu",
        "Format": "2D",
        "CityCount": 7
      }
    ]
  },
  {
    "Title": "School Life",
    "Poster": "https://in.bmscdn.com/events/moviecard/school-life-et00466172-1763361455.jpg",
    "Genres": [
      "Drama",
      "Romantic"
    ],
    "Rating": "A",
    "Duration": "2 hrs 35 mins",
    "EventDate": "2025-11-28",
    "isNewEvent": "Y",
    "CityCount": 7,
    "DefaultEventCode": "ET00466172",
    "Variants": [
      {
        "VariantName": "School Life",
        "EventCode": "ET00466172",
        "Language": "Telugu",
        "Format": "2D",
        "CityCount": 7
      }
    ]
  },
  {
    "Title": "Dies Irae",
    "Poster": "https://in.bmscdn.com/events/moviecard/dies-irae-et00457060-1760593926.jpg",
    "Genres": [
      "Horror",
      "Thriller"
    ],
    "Rating": "A",
    "Duration": "1 hr 55 mins",
    "EventDate": "2025-10-31",
    "isNewEvent": "N",
    "CityCount": 7,
    "DefaultEventCode": "ET00457060",
    "Variants": [
      {
        "VariantName": "Dies Irae",
        "EventCode": "ET00457060",
        "Language": "Malayalam",
        "Format": "2D",
        "CityCount": 7
      }
    ]
  },
  {
    "Title": "The Face of the Faceless",
    "Poster": "https://in.bmscdn.com/events/moviecard/the-face-of-the-faceless-2025-et00470608-1762929995.jpg",
    "Genres": [
      "Drama"
    ],
    "Rating": "UA16",
    "Duration": "2 hrs 16 mins",
    "EventDate": "2025-11-21",
    "isNewEvent": "N",
    "CityCount": 7,
    "DefaultEventCode": "ET00470608",
    "Variants": [
      {
        "VariantName": "The Face of the Faceless",
        "EventCode": "ET00470608",
        "Language": "Telugu",
        "Format": "2D",
        "CityCount": 3
      },
      {
        "VariantName": "The Face of the Faceless (Tamil)",
        "EventCode": "ET00471727",
        "Language": "Tamil",
        "Format": "2D",
        "CityCount": 4
      }
    ]
  },
  {
    "Title": "Spider-Man: Homecoming",
    "Poster": "https://in.bmscdn.com/events/moviecard/spider-man-homecoming-et00059154-01-07-2017-08-06-46.jpg",
    "Genres": [
      "Action",
      "Adventure",
      "Fantasy"
    ],
    "Rating": "UA",
    "Duration": "2 hrs 13 mins",
    "EventDate": "2017-07-07",
    "isNewEvent": "N",
    "CityCount": 7,
    "DefaultEventCode": "ET00045372",
    "Variants": [
      {
        "VariantName": "Spider-Man: Homecoming",
        "EventCode": "ET00045372",
        "Language": "English",
        "Format": "2D",
        "CityCount": 5
      },
      {
        "VariantName": "Spider-Man: Homecoming (3D)",
        "EventCode": "ET00059154",
        "Language": "English",
        "Format": "3D",
        "CityCount": 2
      },
      {
        "VariantName": "Spider-Man: Homecoming (IMAX 3D)",
        "EventCode": "ET00059240",
        "Language": "English",
        "Format": "IMAX 3D",
        "CityCount": 1
      }
    ]
  },
  {
    "Title": "Nirdhar",
    "Poster": "https://in.bmscdn.com/events/moviecard/nirdhar-et00472164-1763983647.jpg",
    "Genres": [
      "Drama",
      "Social",
      "Thriller"
    ],
    "Rating": "UA 7",
    "Duration": "1 hr 47 mins",
    "EventDate": "2025-11-28",
    "isNewEvent": "Y",
    "CityCount": 7,
    "DefaultEventCode": "ET00472164",
    "Variants": [
      {
        "VariantName": "Nirdhar",
        "EventCode": "ET00472164",
        "Language": "Marathi",
        "Format": "2D",
        "CityCount": 7
      }
    ]
  },
  {
    "Title": "Middle Class",
    "Poster": "https://in.bmscdn.com/events/moviecard/middle-class-et00470819-1763016934.jpg",
    "Genres": [
      "Drama",
      "Family"
    ],
    "Rating": "U",
    "Duration": "2 hrs 4 mins",
    "EventDate": "2025-11-21",
    "isNewEvent": "N",
    "CityCount": 7,
    "DefaultEventCode": "ET00470819",
    "Variants": [
      {
        "VariantName": "Middle Class",
        "EventCode": "ET00470819",
        "Language": "Tamil",
        "Format": "2D",
        "CityCount": 7
      }
    ]
  },
  {
    "Title": "Roi Roi Binale",
    "Poster": "https://in.bmscdn.com/events/moviecard/roi-roi-binale-et00467808-1761134846.jpg",
    "Genres": [
      "Drama",
      "Musical"
    ],
    "Rating": "U",
    "Duration": "2 hrs 26 mins",
    "EventDate": "2025-10-31",
    "isNewEvent": "N",
    "CityCount": 6,
    "DefaultEventCode": "ET00467808",
    "Variants": [
      {
        "VariantName": "Roi Roi Binale",
        "EventCode": "ET00467808",
        "Language": "Assamese",
        "Format": "2D",
        "CityCount": 6
      }
    ]
  },
  {
    "Title": "Aavaa De",
    "Poster": "https://in.bmscdn.com/events/moviecard/aavaa-de-et00470116-1762751995.jpg",
    "Genres": [
      "Drama",
      "Musical",
      "Romantic"
    ],
    "Rating": "UA13",
    "Duration": "2 hrs 16 mins",
    "EventDate": "2025-11-28",
    "isNewEvent": "Y",
    "CityCount": 6,
    "DefaultEventCode": "ET00470116",
    "Variants": [
      {
        "VariantName": "Aavaa De",
        "EventCode": "ET00470116",
        "Language": "Gujarati",
        "Format": "2D",
        "CityCount": 6
      }
    ]
  },
  {
    "Title": "Operation London Cafe",
    "Poster": "https://in.bmscdn.com/events/moviecard/after-operation-london-cafe-et00330566-1763121036.jpg",
    "Genres": [
      "Action",
      "Drama"
    ],
    "Rating": "UA16",
    "Duration": "2 hrs 6 mins",
    "EventDate": "2025-11-28",
    "isNewEvent": "Y",
    "CityCount": 6,
    "DefaultEventCode": "ET00330566",
    "Variants": [
      {
        "VariantName": "Operation London Cafe",
        "EventCode": "ET00330566",
        "Language": "Kannada",
        "Format": "2D",
        "CityCount": 6
      }
    ]
  },
  {
    "Title": "Spider-Man: No Way Home",
    "Poster": "https://in.bmscdn.com/events/moviecard/spider-man-no-way-home-et00310790-1691659453.jpg",
    "Genres": [
      "Action",
      "Adventure",
      "Sci-Fi"
    ],
    "Rating": "UA",
    "Duration": "2 hrs 28 mins",
    "EventDate": "2021-12-16",
    "isNewEvent": "N",
    "CityCount": 6,
    "DefaultEventCode": "ET00310790",
    "Variants": [
      {
        "VariantName": "Spider-Man: No Way Home",
        "EventCode": "ET00310790",
        "Language": "English",
        "Format": "2D",
        "CityCount": 5
      },
      {
        "VariantName": "Spider-Man: No Way Home (IMAX 3D)",
        "EventCode": "ET00319200",
        "Language": "English",
        "Format": "IMAX 3D",
        "CityCount": 2
      },
      {
        "VariantName": "Spider-Man: No Way Home (Tamil)",
        "EventCode": "ET00319195",
        "Language": "Tamil",
        "Format": "2D",
        "CityCount": 1
      }
    ]
  },
  {
    "Title": "Kalavari",
    "Poster": "https://in.bmscdn.com/events/moviecard/kalavari-et00472680-1764149010.jpg",
    "Genres": [
      "Drama",
      "Romantic"
    ],
    "Rating": "UA16",
    "Duration": "2 hrs 16 mins",
    "EventDate": "2025-11-28",
    "isNewEvent": "Y",
    "CityCount": 5,
    "DefaultEventCode": "ET00472680",
    "Variants": [
      {
        "VariantName": "Kalavari",
        "EventCode": "ET00472680",
        "Language": "Marathi",
        "Format": "2D",
        "CityCount": 5
      }
    ]
  },
  {
    "Title": "Janatha Bar",
    "Poster": "https://in.bmscdn.com/events/moviecard/janatha-bar-et00472551-1764074344.jpg",
    "Genres": [
      "Action",
      "Drama",
      "Thriller"
    ],
    "Rating": "UA",
    "Duration": "2 hrs 2 mins",
    "EventDate": "2025-11-28",
    "isNewEvent": "Y",
    "CityCount": 5,
    "DefaultEventCode": "ET00472551",
    "Variants": [
      {
        "VariantName": "Janatha Bar",
        "EventCode": "ET00472551",
        "Language": "Telugu",
        "Format": "2D",
        "CityCount": 5
      }
    ]
  },
  {
    "Title": "The Girlfriend",
    "Poster": "https://in.bmscdn.com/events/moviecard/the-girlfriend-et00423419-1733756512.jpg",
    "Genres": [
      "Drama",
      "Romantic"
    ],
    "Rating": "UA13",
    "Duration": "2 hrs 18 mins",
    "EventDate": "2025-11-07",
    "isNewEvent": "N",
    "CityCount": 5,
    "DefaultEventCode": "ET00423419",
    "Variants": [
      {
        "VariantName": "The Girlfriend",
        "EventCode": "ET00423419",
        "Language": "Telugu",
        "Format": "2D",
        "CityCount": 5
      }
    ]
  },
  {
    "Title": "Ikk Kudi",
    "Poster": "https://in.bmscdn.com/events/moviecard/ikk-kudi-et00458910-1756723234.jpg",
    "Genres": [
      "Comedy",
      "Romantic"
    ],
    "Rating": "UA 7",
    "Duration": "2 hrs 3 mins",
    "EventDate": "2025-10-31",
    "isNewEvent": "N",
    "CityCount": 5,
    "DefaultEventCode": "ET00458910",
    "Variants": [
      {
        "VariantName": "Ikk Kudi",
        "EventCode": "ET00458910",
        "Language": "Punjabi",
        "Format": "2D",
        "CityCount": 5
      }
    ]
  },
  {
    "Title": "Mufti Police",
    "Poster": "https://in.bmscdn.com/events/moviecard/mufti-police-et00470953-1763532025.jpg",
    "Genres": [
      "Crime",
      "Thriller"
    ],
    "Rating": "UA16",
    "Duration": "2 hrs 7 mins",
    "EventDate": "2025-11-21",
    "isNewEvent": "N",
    "CityCount": 5,
    "DefaultEventCode": "ET00470953",
    "Variants": [
      {
        "VariantName": "Mufti Police",
        "EventCode": "ET00470953",
        "Language": "Telugu",
        "Format": "2D",
        "CityCount": 5
      }
    ]
  },
  {
    "Title": "Wicked: For Good",
    "Poster": "https://in.bmscdn.com/events/moviecard/wicked-for-good-et00471497-1763461880.jpg",
    "Genres": [
      "Family",
      "Fantasy",
      "Musical"
    ],
    "Rating": "UA16",
    "Duration": "2 hrs 17 mins",
    "EventDate": "2025-11-21",
    "isNewEvent": "N",
    "CityCount": 5,
    "DefaultEventCode": "ET00458691",
    "Variants": [
      {
        "VariantName": "Wicked: For Good",
        "EventCode": "ET00458691",
        "Language": "English",
        "Format": "2D",
        "CityCount": 1
      },
      {
        "VariantName": "Wicked: For Good (3D)",
        "EventCode": "ET00471497",
        "Language": "English",
        "Format": "3D",
        "CityCount": 4
      }
    ]
  },
  {
    "Title": "Rajini Gaang",
    "Poster": "https://in.bmscdn.com/events/moviecard/rajini-gaang-et00472446-1764067337.jpg",
    "Genres": [
      "Comedy",
      "Horror"
    ],
    "Rating": "UA13",
    "Duration": "2 hrs 6 mins",
    "EventDate": "2025-11-27",
    "isNewEvent": "Y",
    "CityCount": 5,
    "DefaultEventCode": "ET00472446",
    "Variants": [
      {
        "VariantName": "Rajini Gaang",
        "EventCode": "ET00472446",
        "Language": "Tamil",
        "Format": "2D",
        "CityCount": 5
      }
    ]
  },
  {
    "Title": "Flirt (Kannada)",
    "Poster": "https://in.bmscdn.com/events/moviecard/flirt-kannada-et00467862-1761200910.jpg",
    "Genres": [
      "Comedy",
      "Romantic",
      "Thriller"
    ],
    "Rating": "UA16",
    "Duration": "2 hrs 44 mins",
    "EventDate": "2025-11-28",
    "isNewEvent": "Y",
    "CityCount": 4,
    "DefaultEventCode": "ET00467862",
    "Variants": [
      {
        "VariantName": "Flirt (Kannada)",
        "EventCode": "ET00467862",
        "Language": "Kannada",
        "Format": "2D",
        "CityCount": 4
      }
    ]
  },
  {
    "Title": "Kantara: A Legend Chapter-1",
    "Poster": "https://in.bmscdn.com/events/moviecard/kantara-a-legend-chapter-1-et00377351-1760336092.jpg",
    "Genres": [
      "Adventure",
      "Drama",
      "Thriller"
    ],
    "Rating": "UA16",
    "Duration": "2 hrs 48 mins",
    "EventDate": "2025-10-02",
    "isNewEvent": "N",
    "CityCount": 4,
    "DefaultEventCode": "ET00377351",
    "Variants": [
      {
        "VariantName": "Kantara: A Legend Chapter-1",
        "EventCode": "ET00377351",
        "Language": "Kannada",
        "Format": "2D",
        "CityCount": 3
      },
      {
        "VariantName": "Kantara: A Legend Chapter-1 (Hindi)",
        "EventCode": "ET00442474",
        "Language": "Hindi",
        "Format": "2D",
        "CityCount": 1
      }
    ]
  },
  {
    "Title": "GST (Ghosts in Trouble)",
    "Poster": "https://in.bmscdn.com/events/moviecard/gst-ghosts-in-trouble-et00471001-1763121678.jpg",
    "Genres": [
      "Comedy",
      "Horror"
    ],
    "Rating": "UA16",
    "Duration": "2 hrs 11 mins",
    "EventDate": "2025-11-28",
    "isNewEvent": "Y",
    "CityCount": 4,
    "DefaultEventCode": "ET00471001",
    "Variants": [
      {
        "VariantName": "GST (Ghosts in Trouble)",
        "EventCode": "ET00471001",
        "Language": "Kannada",
        "Format": "2D",
        "CityCount": 4
      }
    ]
  },
  {
    "Title": "Not All Movies Are The Same: Dual",
    "Poster": "https://in.bmscdn.com/events/moviecard/not-all-movies-are-the-same-dual-et00462838-1763535955.jpg",
    "Genres": [
      "Horror",
      "Mystery",
      "Sci-Fi",
      "Thriller"
    ],
    "Rating": "A",
    "Duration": "1 hr 37 mins",
    "EventDate": "2025-11-28",
    "isNewEvent": "Y",
    "CityCount": 4,
    "DefaultEventCode": "ET00462838",
    "Variants": [
      {
        "VariantName": "Not All Movies Are The Same: Dual",
        "EventCode": "ET00462838",
        "Language": "Telugu",
        "Format": "2D",
        "CityCount": 4
      }
    ]
  },
  {
    "Title": "Victoria",
    "Poster": "https://in.bmscdn.com/events/moviecard/victoria-et00472429-1764049637.jpg",
    "Genres": [
      "Drama"
    ],
    "Rating": "U",
    "Duration": "1 hr 25 mins",
    "EventDate": "2025-11-28",
    "isNewEvent": "Y",
    "CityCount": 4,
    "DefaultEventCode": "ET00472429",
    "Variants": [
      {
        "VariantName": "Victoria",
        "EventCode": "ET00472429",
        "Language": "Malayalam",
        "Format": "2D",
        "CityCount": 4
      }
    ]
  },
  {
    "Title": "Kaantha",
    "Poster": "https://in.bmscdn.com/events/moviecard/kaantha-et00432079-1762856757.jpg",
    "Genres": [
      "Drama",
      "Period",
      "Thriller"
    ],
    "Rating": "UA13",
    "Duration": "2 hrs 43 mins",
    "EventDate": "2025-11-14",
    "isNewEvent": "N",
    "CityCount": 4,
    "DefaultEventCode": "ET00432079",
    "Variants": [
      {
        "VariantName": "Kaantha",
        "EventCode": "ET00432079",
        "Language": "Tamil",
        "Format": "2D",
        "CityCount": 4
      }
    ]
  },
  {
    "Title": "Predator: Badlands",
    "Poster": "https://in.bmscdn.com/events/moviecard/predator-badlands-et00469517-1762407695.jpg",
    "Genres": [
      "Action",
      "Sci-Fi",
      "Thriller"
    ],
    "Rating": "UA16",
    "Duration": "1 hr 47 mins",
    "EventDate": "2025-11-07",
    "isNewEvent": "N",
    "CityCount": 4,
    "DefaultEventCode": "ET00443704",
    "Variants": [
      {
        "VariantName": "Predator: Badlands (4DX 3D)",
        "EventCode": "ET00469517",
        "Language": "English",
        "Format": "4DX 3D",
        "CityCount": 2
      },
      {
        "VariantName": "Predator: Badlands (3D)",
        "EventCode": "ET00469296",
        "Language": "English",
        "Format": "3D",
        "CityCount": 2
      }
    ]
  },
  {
    "Title": "Haati Haati Paa Paa",
    "Poster": "https://in.bmscdn.com/events/moviecard/haati-haati-paa-paa-et00466688-1763455935.jpg",
    "Genres": [
      "Drama",
      "Romantic"
    ],
    "Rating": "UA 7",
    "Duration": "2 hrs 4 mins",
    "EventDate": "2025-11-28",
    "isNewEvent": "Y",
    "CityCount": 3,
    "DefaultEventCode": "ET00466688",
    "Variants": [
      {
        "VariantName": "Haati Haati Paa Paa",
        "EventCode": "ET00466688",
        "Language": "Bengali",
        "Format": "2D",
        "CityCount": 3
      }
    ]
  },
  {
    "Title": "The Taj Story",
    "Poster": "https://in.bmscdn.com/events/moviecard/the-taj-story-et00467657-1763059853.jpg",
    "Genres": [
      "Drama"
    ],
    "Rating": "UA13",
    "Duration": "2 hrs 45 mins",
    "EventDate": "2025-10-31",
    "isNewEvent": "N",
    "CityCount": 3,
    "DefaultEventCode": "ET00467657",
    "Variants": [
      {
        "VariantName": "The Taj Story",
        "EventCode": "ET00467657",
        "Language": "Hindi",
        "Format": "2D",
        "CityCount": 3
      }
    ]
  },
  {
    "Title": "Taath Kana",
    "Poster": "https://in.bmscdn.com/events/moviecard/tath-kana-et00336599-1762150091.jpg",
    "Genres": [
      "Drama"
    ],
    "Rating": "U",
    "Duration": "1 hr 59 mins",
    "EventDate": "2025-11-28",
    "isNewEvent": "Y",
    "CityCount": 3,
    "DefaultEventCode": "ET00336599",
    "Variants": [
      {
        "VariantName": "Taath Kana",
        "EventCode": "ET00336599",
        "Language": "Marathi",
        "Format": "2D",
        "CityCount": 3
      }
    ]
  },
  {
    "Title": "Fakireeyat",
    "Poster": "https://in.bmscdn.com/events/moviecard/fakireeyat-et00455488-1762149872.jpg",
    "Genres": [
      "Devotional",
      "Drama"
    ],
    "Rating": "UA 7",
    "Duration": "2 hrs 30 mins",
    "EventDate": "2025-11-28",
    "isNewEvent": "Y",
    "CityCount": 3,
    "DefaultEventCode": "ET00455488",
    "Variants": [
      {
        "VariantName": "Fakireeyat",
        "EventCode": "ET00455488",
        "Language": "Hindi",
        "Format": "2D",
        "CityCount": 3
      }
    ]
  },
  {
    "Title": "Nayi Idae Yecharikae",
    "Poster": "https://in.bmscdn.com/events/moviecard/nayi-idae-yecharikae-et00470940-1763102229.jpg",
    "Genres": [
      "Horror",
      "Thriller"
    ],
    "Rating": "UA16",
    "Duration": "1 hr 41 mins",
    "EventDate": "2025-11-28",
    "isNewEvent": "Y",
    "CityCount": 3,
    "DefaultEventCode": "ET00470940",
    "Variants": [
      {
        "VariantName": "Nayi Idae Yecharikae",
        "EventCode": "ET00470940",
        "Language": "Kannada",
        "Format": "2D",
        "CityCount": 3
      }
    ]
  },
  {
    "Title": "Gangs of Raipur",
    "Poster": "https://in.bmscdn.com/events/moviecard/gangs-of-raipur-et00471125-1763357195.jpg",
    "Genres": [
      "Action",
      "Crime",
      "Drama"
    ],
    "Rating": "A",
    "Duration": "2 hrs 40 mins",
    "EventDate": "2025-11-28",
    "isNewEvent": "Y",
    "CityCount": 3,
    "DefaultEventCode": "ET00471125",
    "Variants": [
      {
        "VariantName": "Gangs of Raipur",
        "EventCode": "ET00471125",
        "Language": "Hindi",
        "Format": "2D",
        "CityCount": 3
      }
    ]
  },
  {
    "Title": "Now You See Me: Now You Don't",
    "Poster": "https://in.bmscdn.com/events/moviecard/now-you-see-me-now-you-don-t-et00444056-1746003307.jpg",
    "Genres": [
      "Crime",
      "Suspense",
      "Thriller"
    ],
    "Rating": "UA16",
    "Duration": "1 hr 53 mins",
    "EventDate": "2025-11-14",
    "isNewEvent": "N",
    "CityCount": 3,
    "DefaultEventCode": "ET00444056",
    "Variants": [
      {
        "VariantName": "Now You See Me: Now You Don't",
        "EventCode": "ET00444056",
        "Language": "English",
        "Format": "2D",
        "CityCount": 3
      }
    ]
  },
  {
    "Title": "Amarakavyam",
    "Poster": "https://in.bmscdn.com/events/moviecard/amara-kavyam-et00473198-1764413607.jpg",
    "Genres": [
      "Drama",
      "Romantic"
    ],
    "Rating": "UA16",
    "Duration": "2 hrs 49 mins",
    "EventDate": "2025-11-28",
    "isNewEvent": "Y",
    "CityCount": 3,
    "DefaultEventCode": "ET00473198",
    "Variants": [
      {
        "VariantName": "Amarakavyam",
        "EventCode": "ET00473198",
        "Language": "Telugu",
        "Format": "2D",
        "CityCount": 3
      }
    ]
  },
  {
    "Title": "Theeyavar Kulai Nadunga",
    "Poster": "https://in.bmscdn.com/events/moviecard/theeyavar-kulai-nadunga-et00470554-1762928059.jpg",
    "Genres": [
      "Crime",
      "Thriller"
    ],
    "Rating": "UA16",
    "Duration": "2 hrs 7 mins",
    "EventDate": "2025-11-21",
    "isNewEvent": "N",
    "CityCount": 3,
    "DefaultEventCode": "ET00470554",
    "Variants": [
      {
        "VariantName": "Theeyavar Kulai Nadunga",
        "EventCode": "ET00470554",
        "Language": "Tamil",
        "Format": "2D",
        "CityCount": 3
      }
    ]
  },
  {
    "Title": "Ithiri Neram",
    "Poster": "https://in.bmscdn.com/events/moviecard/ithiri-neram-et00467419-1760785131.jpg",
    "Genres": [
      "Drama",
      "Romantic"
    ],
    "Rating": "UA16",
    "Duration": "2 hrs 17 mins",
    "EventDate": "2025-11-07",
    "isNewEvent": "N",
    "CityCount": 3,
    "DefaultEventCode": "ET00467419",
    "Variants": [
      {
        "VariantName": "Ithiri Neram",
        "EventCode": "ET00467419",
        "Language": "Malayalam",
        "Format": "2D",
        "CityCount": 3
      }
    ]
  },
  {
    "Title": "Sisu: Road to Revenge",
    "Poster": "https://in.bmscdn.com/events/moviecard/sisu-road-to-revenge-et00448820-1756470214.jpg",
    "Genres": [
      "Action",
      "War"
    ],
    "Rating": "A",
    "Duration": "1 hr 31 mins",
    "EventDate": "2025-11-21",
    "isNewEvent": "N",
    "CityCount": 3,
    "DefaultEventCode": "ET00448820",
    "Variants": [
      {
        "VariantName": "Sisu: Road to Revenge",
        "EventCode": "ET00448820",
        "Language": "English",
        "Format": "2D",
        "CityCount": 3
      }
    ]
  },
  {
    "Title": "Jai",
    "Poster": "https://in.bmscdn.com/events/moviecard/jai-et00463347-1758175818.jpg",
    "Genres": [
      "Action",
      "Comedy",
      "Drama",
      "Thriller"
    ],
    "Rating": "UA13",
    "Duration": "2 hrs 45 mins",
    "EventDate": "2025-11-14",
    "isNewEvent": "N",
    "CityCount": 3,
    "DefaultEventCode": "ET00463119",
    "Variants": [
      {
        "VariantName": "Jai (Tulu)",
        "EventCode": "ET00463347",
        "Language": "Tulu",
        "Format": "2D",
        "CityCount": 3
      }
    ]
  },
  {
    "Title": "Haq",
    "Poster": "https://in.bmscdn.com/events/moviecard/haq-et00464000-1763107944.jpg",
    "Genres": [
      "Drama",
      "Social"
    ],
    "Rating": "UA13",
    "Duration": "2 hrs 16 mins",
    "EventDate": "2025-11-07",
    "isNewEvent": "N",
    "CityCount": 3,
    "DefaultEventCode": "ET00464000",
    "Variants": [
      {
        "VariantName": "Haq",
        "EventCode": "ET00464000",
        "Language": "Hindi",
        "Format": "2D",
        "CityCount": 3
      }
    ]
  },
  {
    "Title": "Sharthopor",
    "Poster": "https://in.bmscdn.com/events/moviecard/sharthopor-et00464543-1760696056.jpg",
    "Genres": [
      "Drama",
      "Family"
    ],
    "Rating": "UA13",
    "Duration": "2 hrs 15 mins",
    "EventDate": "2025-10-21",
    "isNewEvent": "N",
    "CityCount": 2,
    "DefaultEventCode": "ET00464543",
    "Variants": [
      {
        "VariantName": "Sharthopor",
        "EventCode": "ET00464543",
        "Language": "Bengali",
        "Format": "2D",
        "CityCount": 2
      }
    ]
  },
  {
    "Title": "Thamma",
    "Poster": "https://in.bmscdn.com/events/moviecard/thamma-et00443268-1764092393.jpg",
    "Genres": [
      "Comedy",
      "Horror",
      "Romantic",
      "Supernatural"
    ],
    "Rating": "UA16",
    "Duration": "2 hrs 30 mins",
    "EventDate": "2025-10-21",
    "isNewEvent": "N",
    "CityCount": 2,
    "DefaultEventCode": "ET00443268",
    "Variants": [
      {
        "VariantName": "Thamma",
        "EventCode": "ET00443268",
        "Language": "Hindi",
        "Format": "2D",
        "CityCount": 2
      }
    ]
  },
  {
    "Title": "Smart Sunbai",
    "Poster": "https://in.bmscdn.com/events/moviecard/smart-sunbai-et00465636-1759734158.jpg",
    "Genres": [
      "Comedy",
      "Mystery",
      "Thriller"
    ],
    "Rating": "UA13",
    "Duration": "2 hrs 28 mins",
    "EventDate": "2025-11-21",
    "isNewEvent": "N",
    "CityCount": 2,
    "DefaultEventCode": "ET00465636",
    "Variants": [
      {
        "VariantName": "Smart Sunbai",
        "EventCode": "ET00465636",
        "Language": "Marathi",
        "Format": "2D",
        "CityCount": 2
      }
    ]
  },
  {
    "Title": "Chaniya Toli",
    "Poster": "https://in.bmscdn.com/events/moviecard/chaniya-toli-et00451887-1757313632.jpg",
    "Genres": [
      "Action",
      "Comedy",
      "Crime"
    ],
    "Rating": "UA13",
    "Duration": "2 hrs 12 mins",
    "EventDate": "2025-10-21",
    "isNewEvent": "N",
    "CityCount": 2,
    "DefaultEventCode": "ET00451887",
    "Variants": [
      {
        "VariantName": "Chaniya Toli",
        "EventCode": "ET00451887",
        "Language": "Gujarati",
        "Format": "2D",
        "CityCount": 2
      }
    ]
  },
  {
    "Title": "Raghu Dakat",
    "Poster": "https://in.bmscdn.com/events/moviecard/raghu-dakat-et00428268-1755495684.jpg",
    "Genres": [
      "Action",
      "Drama",
      "Period"
    ],
    "Rating": "UA16",
    "Duration": "2 hrs 32 mins",
    "EventDate": "2025-09-25",
    "isNewEvent": "N",
    "CityCount": 2,
    "DefaultEventCode": "ET00428268",
    "Variants": [
      {
        "VariantName": "Raghu Dakat",
        "EventCode": "ET00428268",
        "Language": "Bengali",
        "Format": "2D",
        "CityCount": 2
      }
    ]
  },
  {
    "Title": "Friday (2025)",
    "Poster": "https://in.bmscdn.com/events/moviecard/friday-2025-et00471000-1763120667.jpg",
    "Genres": [
      "Action",
      "Mystery",
      "Thriller"
    ],
    "Rating": "UA16",
    "Duration": "2 hrs ",
    "EventDate": "2025-11-28",
    "isNewEvent": "Y",
    "CityCount": 2,
    "DefaultEventCode": "ET00471000",
    "Variants": [
      {
        "VariantName": "Friday (2025)",
        "EventCode": "ET00471000",
        "Language": "Tamil",
        "Format": "2D",
        "CityCount": 2
      }
    ]
  },
  {
    "Title": "Godday Godday Chaa 2",
    "Poster": "https://in.bmscdn.com/events/moviecard/godday-godday-chaa-2-et00457013-1762148390.jpg",
    "Genres": [
      "Comedy",
      "Drama"
    ],
    "Rating": "UA13",
    "Duration": "2 hrs 10 mins",
    "EventDate": "2025-10-21",
    "isNewEvent": "N",
    "CityCount": 2,
    "DefaultEventCode": "ET00457013",
    "Variants": [
      {
        "VariantName": "Godday Godday Chaa 2",
        "EventCode": "ET00457013",
        "Language": "Punjabi",
        "Format": "2D",
        "CityCount": 2
      }
    ]
  },
  {
    "Title": "Me No Pause Me Play",
    "Poster": "https://in.bmscdn.com/events/moviecard/me-no-pause-me-play-et00468105-1763448096.jpg",
    "Genres": [
      "Drama",
      "Social"
    ],
    "Rating": "UA13",
    "Duration": "2 hrs 20 mins",
    "EventDate": "2025-11-28",
    "isNewEvent": "Y",
    "CityCount": 2,
    "DefaultEventCode": "ET00468105",
    "Variants": [
      {
        "VariantName": "Me No Pause Me Play",
        "EventCode": "ET00468105",
        "Language": "Hindi",
        "Format": "2D",
        "CityCount": 2
      }
    ]
  },
  {
    "Title": "Asa Mee Ashi Mee",
    "Poster": "https://in.bmscdn.com/events/moviecard/asa-mee-ashi-mee-et00472652-1764141391.jpg",
    "Genres": [
      "Drama",
      "Romantic"
    ],
    "Rating": "UA16",
    "Duration": "1 hr 56 mins",
    "EventDate": "2025-11-28",
    "isNewEvent": "Y",
    "CityCount": 2,
    "DefaultEventCode": "ET00472652",
    "Variants": [
      {
        "VariantName": "Asa Mee Ashi Mee",
        "EventCode": "ET00472652",
        "Language": "Marathi",
        "Format": "2D",
        "CityCount": 2
      }
    ]
  },
  {
    "Title": "12A Railway Colony",
    "Poster": "https://in.bmscdn.com/events/moviecard/12a-railway-colony-et00438736-1763618205.jpg",
    "Genres": [
      "Horror",
      "Thriller"
    ],
    "Rating": "UA16",
    "Duration": "2 hrs 5 mins",
    "EventDate": "2025-11-21",
    "isNewEvent": "N",
    "CityCount": 2,
    "DefaultEventCode": "ET00438736",
    "Variants": [
      {
        "VariantName": "12A Railway Colony",
        "EventCode": "ET00438736",
        "Language": "Telugu",
        "Format": "2D",
        "CityCount": 2
      }
    ]
  },
  {
    "Title": "Dusshera",
    "Poster": "https://in.bmscdn.com/events/moviecard/dusshera-et00466628-1760332691.jpg",
    "Genres": [
      "Mythological",
      "Thriller"
    ],
    "Rating": "UA16",
    "Duration": "2 hrs 18 mins",
    "EventDate": "2025-11-14",
    "isNewEvent": "N",
    "CityCount": 2,
    "DefaultEventCode": "ET00466628",
    "Variants": [
      {
        "VariantName": "Dusshera",
        "EventCode": "ET00466628",
        "Language": "Gujarati",
        "Format": "2D",
        "CityCount": 2
      }
    ]
  },
  {
    "Title": "The Academy of Fine Arts",
    "Poster": "https://in.bmscdn.com/events/moviecard/the-academy-of-fine-arts-et00440981-1761121227.jpg",
    "Genres": [
      "Action",
      "Comedy",
      "Thriller"
    ],
    "Rating": "A",
    "Duration": "2 hrs 29 mins",
    "EventDate": "2025-11-21",
    "isNewEvent": "N",
    "CityCount": 1,
    "DefaultEventCode": "ET00440981",
    "Variants": [
      {
        "VariantName": "The Academy of Fine Arts",
        "EventCode": "ET00440981",
        "Language": "Bengali",
        "Format": "2D",
        "CityCount": 1
      }
    ]
  },
  {
    "Title": "Ek Deewane Ki Deewaniyat",
    "Poster": "https://in.bmscdn.com/events/moviecard/ek-deewane-ki-deewaniyat-et00447585-1756106577.jpg",
    "Genres": [
      "Drama",
      "Romantic",
      "Thriller"
    ],
    "Rating": "A",
    "Duration": "2 hrs 20 mins",
    "EventDate": "2025-10-21",
    "isNewEvent": "N",
    "CityCount": 1,
    "DefaultEventCode": "ET00447585",
    "Variants": [
      {
        "VariantName": "Ek Deewane Ki Deewaniyat",
        "EventCode": "ET00447585",
        "Language": "Hindi",
        "Format": "2D",
        "CityCount": 1
      }
    ]
  },
  {
    "Title": "Misri",
    "Poster": "https://in.bmscdn.com/events/moviecard/misri-et00464386-1761307891.jpg",
    "Genres": [
      "Comedy",
      "Romantic"
    ],
    "Rating": "UA13",
    "Duration": "2 hrs 35 mins",
    "EventDate": "2025-10-31",
    "isNewEvent": "N",
    "CityCount": 1,
    "DefaultEventCode": "ET00464386",
    "Variants": [
      {
        "VariantName": "Misri",
        "EventCode": "ET00464386",
        "Language": "Gujarati",
        "Format": "2D",
        "CityCount": 1
      }
    ]
  },
  {
    "Title": "Paatashaala",
    "Poster": "https://in.bmscdn.com/events/moviecard/paatashaala-et00469230-1762160124.jpg",
    "Genres": [
      "Comedy",
      "Drama"
    ],
    "Rating": "UA13",
    "Duration": "2 hrs 27 mins",
    "EventDate": "2025-11-28",
    "isNewEvent": "Y",
    "CityCount": 1,
    "DefaultEventCode": "ET00469230",
    "Variants": [
      {
        "VariantName": "Paatashaala",
        "EventCode": "ET00469230",
        "Language": "Kannada",
        "Format": "2D",
        "CityCount": 1
      }
    ]
  },
  {
    "Title": "Brat",
    "Poster": "https://in.bmscdn.com/events/moviecard/brat-et00463090-1761807085.jpg",
    "Genres": [
      "Action",
      "Thriller"
    ],
    "Rating": "UA16",
    "Duration": "2 hrs 35 mins",
    "EventDate": "2025-10-31",
    "isNewEvent": "N",
    "CityCount": 1,
    "DefaultEventCode": "ET00463090",
    "Variants": [
      {
        "VariantName": "Brat",
        "EventCode": "ET00463090",
        "Language": "Kannada",
        "Format": "2D",
        "CityCount": 1
      }
    ]
  },
  {
    "Title": "Premante",
    "Poster": "https://in.bmscdn.com/events/moviecard/premante-et00469262-1762167323.jpg",
    "Genres": [
      "Comedy",
      "Drama",
      "Romantic"
    ],
    "Rating": "UA13",
    "Duration": "2 hrs 26 mins",
    "EventDate": "2025-11-21",
    "isNewEvent": "N",
    "CityCount": 1,
    "DefaultEventCode": "ET00469262",
    "Variants": [
      {
        "VariantName": "Premante",
        "EventCode": "ET00469262",
        "Language": "Telugu",
        "Format": "2D",
        "CityCount": 1
      }
    ]
  },
  {
    "Title": "Gatha Vaibhava",
    "Poster": "https://in.bmscdn.com/events/moviecard/gatha-vaibhava-et00437042-1762856505.jpg",
    "Genres": [
      "Drama",
      "Fantasy",
      "Period",
      "Romantic"
    ],
    "Rating": "UA16",
    "Duration": "2 hrs 22 mins",
    "EventDate": "2025-11-14",
    "isNewEvent": "N",
    "CityCount": 1,
    "DefaultEventCode": "ET00437042",
    "Variants": [
      {
        "VariantName": "Gatha Vaibhava",
        "EventCode": "ET00437042",
        "Language": "Kannada",
        "Format": "2D",
        "CityCount": 1
      }
    ]
  },
  {
    "Title": "Bank of Bhagyalakshmi",
    "Poster": "https://in.bmscdn.com/events/moviecard/bank-of-bhagyalakshmi-et00465417-1759487411.jpg",
    "Genres": [
      "Action",
      "Comedy",
      "Crime",
      "Thriller"
    ],
    "Rating": "UA13",
    "Duration": "2 hrs 32 mins",
    "EventDate": "2025-11-27",
    "isNewEvent": "Y",
    "CityCount": 1,
    "DefaultEventCode": "ET00465417",
    "Variants": [
      {
        "VariantName": "Bank of Bhagyalakshmi",
        "EventCode": "ET00465417",
        "Language": "Kannada",
        "Format": "2D",
        "CityCount": 1
      }
    ]
  },
  {
    "Title": "Sarangi",
    "Poster": "https://in.bmscdn.com/events/moviecard/sarangi-et00472072-1763820254.jpg",
    "Genres": [
      "Mystery",
      "Thriller"
    ],
    "Rating": "UA13",
    "Duration": "2 hrs 3 mins",
    "EventDate": "2025-11-28",
    "isNewEvent": "Y",
    "CityCount": 1,
    "DefaultEventCode": "ET00472072",
    "Variants": [
      {
        "VariantName": "Sarangi",
        "EventCode": "ET00472072",
        "Language": "Kannada",
        "Format": "2D",
        "CityCount": 1
      }
    ]
  },
  {
    "Title": "Maanagara Kaaval",
    "Poster": "https://in.bmscdn.com/events/moviecard/maanagara-kaaval-et00082891-1726138359.jpg",
    "Genres": [
      "Action",
      "Political",
      "Thriller"
    ],
    "Rating": "UA",
    "Duration": "2 hrs 30 mins",
    "EventDate": "1991-06-28",
    "isNewEvent": "N",
    "CityCount": 1,
    "DefaultEventCode": "ET00082891",
    "Variants": [
      {
        "VariantName": "Maanagara Kaaval",
        "EventCode": "ET00082891",
        "Language": "Tamil",
        "Format": "2D",
        "CityCount": 1
      }
    ]
  },
  {
    "Title": "Vellakuthira",
    "Poster": "https://in.bmscdn.com/events/moviecard/vellakuthira-et00468314-1763706856.jpg",
    "Genres": [
      "Drama"
    ],
    "Rating": "U",
    "Duration": "2 hrs 5 mins",
    "EventDate": "2025-11-28",
    "isNewEvent": "Y",
    "CityCount": 1,
    "DefaultEventCode": "ET00468314",
    "Variants": [
      {
        "VariantName": "Vellakuthira",
        "EventCode": "ET00468314",
        "Language": "Tamil",
        "Format": "2D",
        "CityCount": 1
      }
    ]
  },
  {
    "Title": "The Pet Detective",
    "Poster": "https://in.bmscdn.com/events/moviecard/the-pet-detective-et00465248-1759316590.jpg",
    "Genres": [
      "Comedy",
      "Mystery",
      "Thriller"
    ],
    "Rating": "U",
    "Duration": "1 hr 58 mins",
    "EventDate": "2025-10-16",
    "isNewEvent": "N",
    "CityCount": 1,
    "DefaultEventCode": "ET00465248",
    "Variants": [
      {
        "VariantName": "The Pet Detective",
        "EventCode": "ET00465248",
        "Language": "Malayalam",
        "Format": "2D",
        "CityCount": 1
      }
    ]
  },
  {
    "Title": "Lokah: Chapter 1 - Chandra",
    "Poster": "https://in.bmscdn.com/events/moviecard/lokah-chapter-1--chandra-et00456016-1753856507.jpg",
    "Genres": [
      "Action",
      "Comedy",
      "Fantasy"
    ],
    "Rating": "UA16",
    "Duration": "2 hrs 31 mins",
    "EventDate": "2025-08-28",
    "isNewEvent": "N",
    "CityCount": 1,
    "DefaultEventCode": "ET00456016",
    "Variants": [
      {
        "VariantName": "Lokah: Chapter 1 - Chandra",
        "EventCode": "ET00456016",
        "Language": "Malayalam",
        "Format": "2D",
        "CityCount": 1
      }
    ]
  },
  {
    "Title": "Naangal",
    "Poster": "https://in.bmscdn.com/events/moviecard/naangal-et00442117-1744781287.jpg",
    "Genres": [
      "Drama"
    ],
    "Rating": "UA13",
    "Duration": "2 hrs 31 mins",
    "EventDate": "2025-04-18",
    "isNewEvent": "N",
    "CityCount": 1,
    "DefaultEventCode": "ET00442117",
    "Variants": [
      {
        "VariantName": "Naangal",
        "EventCode": "ET00442117",
        "Language": "Tamil",
        "Format": "2D",
        "CityCount": 1
      }
    ]
  },
  {
    "Title": "Uut: Bhavanancha Udrek",
    "Poster": "https://in.bmscdn.com/events/moviecard/uut-bhavanancha-udrek-et00467167-1760615045.jpg",
    "Genres": [
      "Action",
      "Drama",
      "Romantic"
    ],
    "Rating": "UA",
    "Duration": "2 hrs ",
    "EventDate": "2025-11-21",
    "isNewEvent": "N",
    "CityCount": 1,
    "DefaultEventCode": "ET00467167",
    "Variants": [
      {
        "VariantName": "Uut: Bhavanancha Udrek",
        "EventCode": "ET00467167",
        "Language": "Marathi",
        "Format": "2D",
        "CityCount": 1
      }
    ]
  },
  {
    "Title": "Janam (2025)",
    "Poster": "https://in.bmscdn.com/events/moviecard/janam-2025-et00472449-1764067605.jpg",
    "Genres": [
      "Drama",
      "Thriller"
    ],
    "Rating": "UA",
    "Duration": "2 hrs 8 mins",
    "EventDate": "2025-11-28",
    "isNewEvent": "Y",
    "CityCount": 1,
    "DefaultEventCode": "ET00472449",
    "Variants": [
      {
        "VariantName": "Janam (2025)",
        "EventCode": "ET00472449",
        "Language": "Telugu",
        "Format": "2D",
        "CityCount": 1
      }
    ]
  },
  {
    "Title": "O ",
    "Poster": "https://in.bmscdn.com/events/moviecard/o-et00023128-1764430696.jpg",
    "Genres": [
      "Drama"
    ],
    "Rating": "-",
    "Duration": "-",
    "EventDate": "2014-07-18",
    "isNewEvent": "N",
    "CityCount": 1,
    "DefaultEventCode": "ET00023128",
    "Variants": [
      {
        "VariantName": "O (Tamil)",
        "EventCode": "ET00023128",
        "Language": "Tamil",
        "Format": "2D",
        "CityCount": 1
      }
    ]
  },
  {
    "Title": "The House of Dead (7D)",
    "Poster": "https://in.bmscdn.com/events/moviecard/the-house-of-dead-7d-et00434744-1740047746.jpg",
    "Genres": [
      "Drama"
    ],
    "Rating": "",
    "Duration": "-",
    "EventDate": "2025-02-21",
    "isNewEvent": "N",
    "CityCount": 1,
    "DefaultEventCode": "ET00434744",
    "Variants": [
      {
        "VariantName": "The House of Dead (7D)",
        "EventCode": "ET00434744",
        "Language": "English",
        "Format": "7D",
        "CityCount": 1
      }
    ]
  },
  {
    "Title": "Pre Historic Adventure",
    "Poster": "https://in.bmscdn.com/events/moviecard/pre-historic-adventure-et00023755-1740549143.jpg",
    "Genres": [
      "Adventure"
    ],
    "Rating": "",
    "Duration": "-",
    "EventDate": "2014-08-30",
    "isNewEvent": "N",
    "CityCount": 1,
    "DefaultEventCode": "ET00023755",
    "Variants": [
      {
        "VariantName": "Pre Historic Adventure 7D",
        "EventCode": "ET00023755",
        "Language": "English 7D",
        "Format": "7D",
        "CityCount": 1
      }
    ]
  },
  {
    "Title": "Temple Run",
    "Poster": "https://in.bmscdn.com/events/moviecard/temple-run-et00027146-1737715315.jpg",
    "Genres": [
      "Adventure"
    ],
    "Rating": "",
    "Duration": "-",
    "EventDate": "2016-05-17",
    "isNewEvent": "N",
    "CityCount": 1,
    "DefaultEventCode": "ET00027146",
    "Variants": [
      {
        "VariantName": "Temple Run 7D- Combo",
        "EventCode": "ET00027146",
        "Language": "English 7D",
        "Format": "7D",
        "CityCount": 1
      }
    ]
  },
  {
    "Title": "Khaidu",
    "Poster": "https://in.bmscdn.com/events/moviecard/khaidu-et00472092-1763801099.jpg",
    "Genres": [
      "Suspense",
      "Thriller"
    ],
    "Rating": "UA",
    "Duration": "2 hrs 7 mins",
    "EventDate": "2025-11-28",
    "isNewEvent": "Y",
    "CityCount": 1,
    "DefaultEventCode": "ET00472092",
    "Variants": [
      {
        "VariantName": "Khaidu",
        "EventCode": "ET00472092",
        "Language": "Telugu",
        "Format": "2D",
        "CityCount": 1
      }
    ]
  },
  {
    "Title": "Rickshawkaran",
    "Poster": "https://in.bmscdn.com/events/moviecard/rickshawkaran-et00047023-28-09-2016-01-35-26.jpg",
    "Genres": [
      "Action",
      "Drama"
    ],
    "Rating": "U",
    "Duration": "2 hrs 45 mins",
    "EventDate": "1971-01-01",
    "isNewEvent": "N",
    "CityCount": 1,
    "DefaultEventCode": "ET00047023",
    "Variants": [
      {
        "VariantName": "Rickshawkaran",
        "EventCode": "ET00047023",
        "Language": "Tamil",
        "Format": "2D",
        "CityCount": 1
      }
    ]
  },
  {
    "Title": "Aan Paavam Pollathathu",
    "Poster": "https://in.bmscdn.com/events/moviecard/aan-paavam-pollathathu-et00468153-1761386182.jpg",
    "Genres": [
      "Comedy",
      "Drama"
    ],
    "Rating": "UA13",
    "Duration": "2 hrs 2 mins",
    "EventDate": "2025-10-31",
    "isNewEvent": "N",
    "CityCount": 1,
    "DefaultEventCode": "ET00468153",
    "Variants": [
      {
        "VariantName": "Aan Paavam Pollathathu",
        "EventCode": "ET00468153",
        "Language": "Tamil",
        "Format": "2D",
        "CityCount": 1
      }
    ]
  },
  {
    "Title": "Aaromaley",
    "Poster": "https://in.bmscdn.com/events/moviecard/aaromaley-et00468371-1762256128.jpg",
    "Genres": [
      "Comedy",
      "Romantic"
    ],
    "Rating": "UA13",
    "Duration": "2 hrs 7 mins",
    "EventDate": "2025-11-07",
    "isNewEvent": "N",
    "CityCount": 1,
    "DefaultEventCode": "ET00468371",
    "Variants": [
      {
        "VariantName": "Aaromaley",
        "EventCode": "ET00468371",
        "Language": "Tamil",
        "Format": "2D",
        "CityCount": 1
      }
    ]
  },
  {
    "Title": "Ondimuniyum Nallapadanum",
    "Poster": "https://in.bmscdn.com/events/moviecard/ondimuniyum-nallapadanum-et00470042-1762515554.jpg",
    "Genres": [
      "Comedy",
      "Drama"
    ],
    "Rating": "U",
    "Duration": "2 hrs 1 min",
    "EventDate": "2025-11-28",
    "isNewEvent": "Y",
    "CityCount": 1,
    "DefaultEventCode": "ET00470042",
    "Variants": [
      {
        "VariantName": "Ondimuniyum Nallapadanum",
        "EventCode": "ET00470042",
        "Language": "Tamil",
        "Format": "2D",
        "CityCount": 1
      }
    ]
  },
  {
    "Title": "Kishkindhapuri (Hindi)",
    "Poster": "https://in.bmscdn.com/events/moviecard/kishkindhapuri-hindi-et00465951-1759915702.jpg",
    "Genres": [
      "Horror",
      "Mystery",
      "Thriller"
    ],
    "Rating": "A",
    "Duration": "2 hrs 5 mins",
    "EventDate": "2025-10-10",
    "isNewEvent": "N",
    "CityCount": 1,
    "DefaultEventCode": "ET00465951",
    "Variants": [
      {
        "VariantName": "Kishkindhapuri (Hindi)",
        "EventCode": "ET00465951",
        "Language": "Hindi",
        "Format": "2D",
        "CityCount": 1
      }
    ]
  },
  {
    "Title": "Snake Cave",
    "Poster": "https://in.bmscdn.com/events/moviecard/snake-cave-et00357932-1682320847.jpg",
    "Genres": [
      "Action",
      "Adventure",
      "Thriller"
    ],
    "Rating": "UA",
    "Duration": "1 hr 38 mins",
    "EventDate": "2023-07-21",
    "isNewEvent": "N",
    "CityCount": 1,
    "DefaultEventCode": "ET00357932",
    "Variants": [
      {
        "VariantName": "Snake Cave",
        "EventCode": "ET00357932",
        "Language": "Hindi",
        "Format": "2D",
        "CityCount": 1
      }
    ]
  },
  {
    "Title": "Mass Jathara",
    "Poster": "https://in.bmscdn.com/events/moviecard/mass-jathara-et00418116-1761711200.jpg",
    "Genres": [
      "Action",
      "Drama"
    ],
    "Rating": "UA16",
    "Duration": "2 hrs 25 mins",
    "EventDate": "2025-10-31",
    "isNewEvent": "N",
    "CityCount": 1,
    "DefaultEventCode": "ET00418116",
    "Variants": [
      {
        "VariantName": "Mass Jathara",
        "EventCode": "ET00418116",
        "Language": "Telugu",
        "Format": "2D",
        "CityCount": 1
      }
    ]
  },
  {
    "Title": "Poseidon Rex",
    "Poster": "https://in.bmscdn.com/events/moviecard/poseidon-rex-et00471219-1763359193.jpg",
    "Genres": [
      "Action",
      "Adventure",
      "Drama",
      "Thriller"
    ],
    "Rating": "A",
    "Duration": "1 hr 21 mins",
    "EventDate": "2014-06-06",
    "isNewEvent": "N",
    "CityCount": 1,
    "DefaultEventCode": "ET00038221",
    "Variants": [
      {
        "VariantName": "Poseidon Rex (Telugu)",
        "EventCode": "ET00471219",
        "Language": "Telugu",
        "Format": "2D",
        "CityCount": 1
      }
    ]
  },
  {
    "Title": "Tantra (2025)",
    "Poster": "https://in.bmscdn.com/events/moviecard/tantra-2025-et00470001-1762501813.jpg",
    "Genres": [
      "Drama",
      "Psychological",
      "Thriller"
    ],
    "Rating": "UA16",
    "Duration": "1 hr 48 mins",
    "EventDate": "2025-11-28",
    "isNewEvent": "Y",
    "CityCount": 1,
    "DefaultEventCode": "ET00470001",
    "Variants": [
      {
        "VariantName": "Tantra (2025)",
        "EventCode": "ET00470001",
        "Language": "Kannada",
        "Format": "2D",
        "CityCount": 1
      }
    ]
  },
  {
    "Title": "Udaala",
    "Poster": "https://in.bmscdn.com/events/moviecard/udaala-et00469786-1762417653.jpg",
    "Genres": [
      "Drama",
      "Romantic"
    ],
    "Rating": "UA16",
    "Duration": "2 hrs 42 mins",
    "EventDate": "2025-11-14",
    "isNewEvent": "N",
    "CityCount": 1,
    "DefaultEventCode": "ET00469786",
    "Variants": [
      {
        "VariantName": "Udaala",
        "EventCode": "ET00469786",
        "Language": "Kannada",
        "Format": "2D",
        "CityCount": 1
      }
    ]
  },
  {
    "Title": "Yellow (2025)",
    "Poster": "https://in.bmscdn.com/events/moviecard/yellow-2025-et00470043-1763102438.jpg",
    "Genres": [
      "Drama",
      "Romantic"
    ],
    "Rating": "UA13",
    "Duration": "2 hrs 16 mins",
    "EventDate": "2025-11-21",
    "isNewEvent": "N",
    "CityCount": 1,
    "DefaultEventCode": "ET00470043",
    "Variants": [
      {
        "VariantName": "Yellow (2025)",
        "EventCode": "ET00470043",
        "Language": "Tamil",
        "Format": "2D",
        "CityCount": 1
      }
    ]
  },
  {
    "Title": "Bison Kaalamaadan",
    "Poster": "https://in.bmscdn.com/events/moviecard/bison-kaalamaadan-et00462034-1757487998.jpg",
    "Genres": [
      "Action",
      "Crime",
      "Drama"
    ],
    "Rating": "UA16",
    "Duration": "2 hrs 48 mins",
    "EventDate": "2025-10-17",
    "isNewEvent": "N",
    "CityCount": 1,
    "DefaultEventCode": "ET00462034",
    "Variants": [
      {
        "VariantName": "Bison Kaalamaadan",
        "EventCode": "ET00462034",
        "Language": "Tamil",
        "Format": "2D",
        "CityCount": 1
      }
    ]
  },
  {
    "Title": "Dawood",
    "Poster": "https://in.bmscdn.com/events/moviecard/dawood-et00461334-1757313369.jpg",
    "Genres": [
      "Comedy",
      "Crime",
      "Thriller"
    ],
    "Rating": "UA16",
    "Duration": "2 hrs 2 mins",
    "EventDate": "2025-11-14",
    "isNewEvent": "N",
    "CityCount": 1,
    "DefaultEventCode": "ET00461334",
    "Variants": [
      {
        "VariantName": "Dawood",
        "EventCode": "ET00461334",
        "Language": "Tamil",
        "Format": "2D",
        "CityCount": 1
      }
    ]
  },
  {
    "Title": "Asambhav",
    "Poster": "https://in.bmscdn.com/events/moviecard/asambhav-et00467711-1762755288.jpg",
    "Genres": [
      "Mystery",
      "Romantic",
      "Thriller"
    ],
    "Rating": "UA16",
    "Duration": "2 hrs 20 mins",
    "EventDate": "2025-11-21",
    "isNewEvent": "N",
    "CityCount": 1,
    "DefaultEventCode": "ET00467711",
    "Variants": [
      {
        "VariantName": "Asambhav",
        "EventCode": "ET00467711",
        "Language": "Marathi",
        "Format": "2D",
        "CityCount": 1
      }
    ]
  },
  {
    "Title": "Gondhal",
    "Poster": "https://in.bmscdn.com/events/moviecard/gondhal-et00465382-1764478831.jpg",
    "Genres": [
      "Drama",
      "Thriller"
    ],
    "Rating": "UA16",
    "Duration": "2 hrs ",
    "EventDate": "2025-11-14",
    "isNewEvent": "N",
    "CityCount": 1,
    "DefaultEventCode": "ET00465382",
    "Variants": [
      {
        "VariantName": "Gondhal",
        "EventCode": "ET00465382",
        "Language": "Marathi",
        "Format": "2D",
        "CityCount": 1
      }
    ]
  },
  {
    "Title": "Abhanga Tukaram",
    "Poster": "https://in.bmscdn.com/events/moviecard/abhanga-tukaram-et00463835-1758527906.jpg",
    "Genres": [
      "Biography",
      "Drama",
      "Historical"
    ],
    "Rating": "U",
    "Duration": "2 hrs 15 mins",
    "EventDate": "2025-11-07",
    "isNewEvent": "N",
    "CityCount": 1,
    "DefaultEventCode": "ET00463835",
    "Variants": [
      {
        "VariantName": "Abhanga Tukaram",
        "EventCode": "ET00463835",
        "Language": "Marathi",
        "Format": "2D",
        "CityCount": 1
      }
    ]
  },
  {
    "Title": "Kaisi Ye Paheli",
    "Poster": "https://in.bmscdn.com/events/moviecard/kaisi-ye-paheli-et00469366-1762237312.jpg",
    "Genres": [
      "Mystery",
      "Thriller"
    ],
    "Rating": "UA16",
    "Duration": "1 hr 41 mins",
    "EventDate": "2025-11-28",
    "isNewEvent": "Y",
    "CityCount": 1,
    "DefaultEventCode": "ET00469366",
    "Variants": [
      {
        "VariantName": "Kaisi Ye Paheli",
        "EventCode": "ET00469366",
        "Language": "Hindi",
        "Format": "2D",
        "CityCount": 1
      }
    ]
  },
  {
    "Title": "Sivakamyin Selvan",
    "Poster": "https://in.bmscdn.com/events/moviecard/sivakamyin-selvan-et00040489-30-09-2020-11-21-30.jpg",
    "Genres": [
      "Drama",
      "Family",
      "Romantic"
    ],
    "Rating": "U",
    "Duration": "2 hrs 34 mins",
    "EventDate": "1974-01-26",
    "isNewEvent": "N",
    "CityCount": 1,
    "DefaultEventCode": "ET00040489",
    "Variants": [
      {
        "VariantName": "Sivakamyin Selvan",
        "EventCode": "ET00040489",
        "Language": "Tamil",
        "Format": "2D",
        "CityCount": 1
      }
    ]
  },
  {
    "Title": "Lokkhikantopur Local",
    "Poster": "https://in.bmscdn.com/events/moviecard/lokkhikantopur-local-et00470266-1762763385.jpg",
    "Genres": [
      "Drama",
      "Social"
    ],
    "Rating": "UA16",
    "Duration": "2 hrs 39 mins",
    "EventDate": "2025-11-21",
    "isNewEvent": "N",
    "CityCount": 1,
    "DefaultEventCode": "ET00470266",
    "Variants": [
      {
        "VariantName": "Lokkhikantopur Local",
        "EventCode": "ET00470266",
        "Language": "Bengali",
        "Format": "2D",
        "CityCount": 1
      }
    ]
  }
]